john_robert/__init__.py
john_robert/about_me.py
john_robert-0.1.0.dist-info/LICENSE
john_robert-0.1.0.dist-info/METADATA
john_robert-0.1.0.dist-info/WHEEL
john_robert-0.1.0.dist-info/top_level.txt
john_robert-0.1.0.dist-info/RECORD
